{
  "annotations": {
    "list": [
      {
        "builtIn": 1,
        "datasource": "-- Grafana --",
        "enable": true,
        "hide": true,
        "iconColor": "rgba(0, 211, 255, 1)",
        "name": "Annotations & Alerts",
        "target": {
          "limit": 100,
          "matchAny": false,
          "tags": [],
          "type": "dashboard"
        },
        "type": "dashboard"
      }
    ]
  },
  "editable": true,
  "fiscalYearStartMonth": 0,
  "graphTooltip": 0,
  "links": [],
  "liveNow": false,
  "panels": [
    {
      "fieldConfig": {
        "defaults": {
          "color": {
            "mode": "thresholds"
          },
          "mappings": [],
          "thresholds": {
            "mode": "absolute",
            "steps": [
              {
                "color": "blue",
                "value": null
              },
              {
                "color": "green",
                "value": 17
              },
              {
                "color": "red",
                "value": 30
              }
            ]
          },
          "unit": "celsius"
        },
        "overrides": []
      },
      "gridPos": {
        "h": 8,
        "w": 6,
        "x": 0,
        "y": 0
      },
      "id": 9,
      "options": {
        "colorMode": "value",
        "graphMode": "area",
        "justifyMode": "auto",
        "orientation": "auto",
        "reduceOptions": {
          "calcs": [
            "lastNotNull"
          ],
          "fields": "",
          "values": false
        },
        "text": {},
        "textMode": "auto"
      },
      "pluginVersion": "8.3.4",
      "targets": [
        {
          "groupBy": [
            {
              "params": [
                "$__interval"
              ],
              "type": "time"
            },
            {
              "params": [
                "null"
              ],
              "type": "fill"
            }
          ],
          "measurement": "xymd1",
          "orderByTime": "ASC",
          "policy": "default",
          "refId": "A",
          "resultFormat": "time_series",
          "select": [
            [
              {
                "params": [
                  "t"
                ],
                "type": "field"
              },
              {
                "params": [],
                "type": "mean"
              }
            ]
          ],
          "tags": [
            {
              "key": "device.name",
              "operator": "=",
              "value": "controlbox"
            }
          ]
        }
      ],
      "title": "Temperature",
      "type": "stat"
    },
    {
      "fieldConfig": {
        "defaults": {
          "color": {
            "mode": "thresholds"
          },
          "mappings": [],
          "thresholds": {
            "mode": "absolute",
            "steps": [
              {
                "color": "yellow",
                "value": null
              },
              {
                "color": "green",
                "value": 49
              },
              {
                "color": "red",
                "value": 58
              }
            ]
          },
          "unit": "humidity"
        },
        "overrides": []
      },
      "gridPos": {
        "h": 8,
        "w": 6,
        "x": 6,
        "y": 0
      },
      "id": 10,
      "options": {
        "colorMode": "value",
        "graphMode": "area",
        "justifyMode": "auto",
        "orientation": "auto",
        "reduceOptions": {
          "calcs": [
            "lastNotNull"
          ],
          "fields": "",
          "values": false
        },
        "text": {},
        "textMode": "auto"
      },
      "pluginVersion": "8.3.4",
      "targets": [
        {
          "groupBy": [
            {
              "params": [
                "$__interval"
              ],
              "type": "time"
            },
            {
              "params": [
                "null"
              ],
              "type": "fill"
            }
          ],
          "measurement": "xymd1",
          "orderByTime": "ASC",
          "policy": "default",
          "refId": "A",
          "resultFormat": "time_series",
          "select": [
            [
              {
                "params": [
                  "h"
                ],
                "type": "field"
              },
              {
                "params": [],
                "type": "mean"
              }
            ]
          ],
          "tags": [
            {
              "key": "device.name",
              "operator": "=",
              "value": "controlbox"
            }
          ]
        }
      ],
      "title": "Humidity",
      "type": "stat"
    },
    {
      "alert": {
        "alertRuleTags": {},
        "conditions": [
          {
            "evaluator": {
              "params": [
                5,
                35
              ],
              "type": "outside_range"
            },
            "operator": {
              "type": "and"
            },
            "query": {
              "params": [
                "temperature",
                "5m",
                "now"
              ]
            },
            "reducer": {
              "params": [],
              "type": "avg"
            },
            "type": "query"
          }
        ],
        "executionErrorState": "alerting",
        "for": "5m",
        "frequency": "1m",
        "handler": 1,
        "message": "Outside range 5-35 deg C",
        "name": "Temperature alert",
        "noDataState": "no_data",
        "notifications": []
      },
      "fieldConfig": {
        "defaults": {
          "color": {
            "mode": "palette-classic"
          },
          "custom": {
            "axisLabel": "",
            "axisPlacement": "auto",
            "barAlignment": 0,
            "drawStyle": "line",
            "fillOpacity": 0,
            "gradientMode": "none",
            "hideFrom": {
              "legend": false,
              "tooltip": false,
              "viz": false
            },
            "lineInterpolation": "linear",
            "lineWidth": 1,
            "pointSize": 5,
            "scaleDistribution": {
              "type": "linear"
            },
            "showPoints": "auto",
            "spanNulls": false,
            "stacking": {
              "group": "A",
              "mode": "none"
            },
            "thresholdsStyle": {
              "mode": "area"
            }
          },
          "mappings": [],
          "thresholds": {
            "mode": "absolute",
            "steps": [
              {
                "color": "blue",
                "value": null
              },
              {
                "color": "green",
                "value": 5
              },
              {
                "color": "red",
                "value": 35
              }
            ]
          },
          "unit": "celsius"
        },
        "overrides": []
      },
      "gridPos": {
        "h": 9,
        "w": 12,
        "x": 0,
        "y": 8
      },
      "id": 5,
      "options": {
        "legend": {
          "calcs": [
            "max",
            "min"
          ],
          "displayMode": "list",
          "placement": "bottom"
        },
        "tooltip": {
          "mode": "single"
        }
      },
      "targets": [
        {
          "groupBy": [
            {
              "params": [
                "$__interval"
              ],
              "type": "time"
            },
            {
              "params": [
                "null"
              ],
              "type": "fill"
            }
          ],
          "measurement": "xymd1",
          "orderByTime": "ASC",
          "policy": "default",
          "refId": "temperature",
          "resultFormat": "time_series",
          "select": [
            [
              {
                "params": [
                  "t"
                ],
                "type": "field"
              },
              {
                "params": [],
                "type": "mean"
              }
            ]
          ],
          "tags": [
            {
              "key": "device.name",
              "operator": "=",
              "value": "controlbox"
            },
            {
              "condition": "AND",
              "key": "t",
              "operator": "<",
              "value": "80"
            }
          ]
        }
      ],
      "thresholds": [
        {
          "colorMode": "critical",
          "op": "lt",
          "value": 5,
          "visible": true
        },
        {
          "colorMode": "critical",
          "op": "gt",
          "value": 35,
          "visible": true
        }
      ],
      "title": "Temperature",
      "type": "timeseries"
    },
    {
      "alert": {
        "alertRuleTags": {},
        "conditions": [
          {
            "evaluator": {
              "params": [
                15,
                85
              ],
              "type": "outside_range"
            },
            "operator": {
              "type": "and"
            },
            "query": {
              "params": [
                "humidity",
                "5m",
                "now"
              ]
            },
            "reducer": {
              "params": [],
              "type": "avg"
            },
            "type": "query"
          }
        ],
        "executionErrorState": "alerting",
        "for": "5m",
        "frequency": "1m",
        "handler": 1,
        "message": "Outside range 15-85 %H",
        "name": "Humidity alert",
        "noDataState": "no_data",
        "notifications": []
      },
      "fieldConfig": {
        "defaults": {
          "color": {
            "mode": "palette-classic"
          },
          "custom": {
            "axisLabel": "",
            "axisPlacement": "auto",
            "barAlignment": 0,
            "drawStyle": "line",
            "fillOpacity": 0,
            "gradientMode": "none",
            "hideFrom": {
              "legend": false,
              "tooltip": false,
              "viz": false
            },
            "lineInterpolation": "linear",
            "lineWidth": 1,
            "pointSize": 5,
            "scaleDistribution": {
              "type": "linear"
            },
            "showPoints": "auto",
            "spanNulls": false,
            "stacking": {
              "group": "A",
              "mode": "none"
            },
            "thresholdsStyle": {
              "mode": "area"
            }
          },
          "decimals": 0,
          "mappings": [],
          "thresholds": {
            "mode": "absolute",
            "steps": [
              {
                "color": "orange",
                "value": null
              },
              {
                "color": "green",
                "value": 15
              },
              {
                "color": "red",
                "value": 85
              }
            ]
          },
          "unit": "humidity"
        },
        "overrides": []
      },
      "gridPos": {
        "h": 9,
        "w": 12,
        "x": 0,
        "y": 17
      },
      "id": 3,
      "options": {
        "legend": {
          "calcs": [
            "min",
            "max"
          ],
          "displayMode": "list",
          "placement": "bottom"
        },
        "tooltip": {
          "mode": "single"
        }
      },
      "targets": [
        {
          "alias": "humidity",
          "groupBy": [
            {
              "params": [
                "$__interval"
              ],
              "type": "time"
            },
            {
              "params": [
                "null"
              ],
              "type": "fill"
            }
          ],
          "hide": false,
          "measurement": "xymd1",
          "orderByTime": "ASC",
          "policy": "default",
          "refId": "humidity",
          "resultFormat": "time_series",
          "select": [
            [
              {
                "params": [
                  "h"
                ],
                "type": "field"
              },
              {
                "params": [],
                "type": "mean"
              }
            ]
          ],
          "tags": [
            {
              "key": "device.name",
              "operator": "=",
              "value": "controlbox"
            }
          ]
        }
      ],
      "thresholds": [
        {
          "colorMode": "critical",
          "op": "lt",
          "value": 15,
          "visible": true
        },
        {
          "colorMode": "critical",
          "op": "gt",
          "value": 85,
          "visible": true
        }
      ],
      "title": "Humidity",
      "type": "timeseries"
    }
  ],
  "refresh": "",
  "schemaVersion": 34,
  "style": "dark",
  "tags": [],
  "templating": {
    "list": []
  },
  "time": {
    "from": "now-90d",
    "to": "now"
  },
  "timepicker": {},
  "timezone": "",
  "title": "Controlbox",
  "uid": "4lHa0Dd7k",
  "version": 1,
  "weekStart": ""
}
